LICENSE
MANIFEST.in
README.rst
checkout.xml
defaults.xml
setup.cfg
setup.py
./__init__.py
./checkout.py
./checkout.xml
./configuration.py
./i18n.py
./payment.py
./sale.py
./signals.py
./tryton.cfg
./locale/de_DE.po
./tests/__init__.py
./tests/test_address.py
./tests/test_checkout.py
./tests/test_payment.py
./view/address_form.xml
./view/website_checkout.xml
locale/de_DE.po
trytond_nereid_checkout.egg-info/PKG-INFO
trytond_nereid_checkout.egg-info/SOURCES.txt
trytond_nereid_checkout.egg-info/dependency_links.txt
trytond_nereid_checkout.egg-info/entry_points.txt
trytond_nereid_checkout.egg-info/not-zip-safe
trytond_nereid_checkout.egg-info/requires.txt
trytond_nereid_checkout.egg-info/top_level.txt